scripts/__init__.py
scripts/__version__.py
scripts/cli.py
scripts/frida_github.py
scripts/logger.py
tests/__init__.py
tests/test_cli.py
frida_gadget-1.3.6.dist-info/LICENSE
frida_gadget-1.3.6.dist-info/METADATA
frida_gadget-1.3.6.dist-info/WHEEL
frida_gadget-1.3.6.dist-info/entry_points.txt
frida_gadget-1.3.6.dist-info/top_level.txt
frida_gadget-1.3.6.dist-info/RECORD
