Metadata-Version: 2.1
Name: frida-gadget
Version: 1.3.6
Summary: Automated Frida Gadget injection tool
Home-page: https://github.com/ksg97031/frida-gadget
Author: ksg97031
Author-email: ksg97031@gmail.com
Classifier: Programming Language :: Python :: 3.6
Classifier: Programming Language :: Python :: 3.7
Classifier: Programming Language :: Python :: 3.8
Classifier: Programming Language :: Python :: 3.9
Classifier: Programming Language :: Python :: 3.10
Classifier: Programming Language :: Python :: 3.11
Classifier: License :: OSI Approved :: MIT License
Classifier: Operating System :: OS Independent
Requires-Python: >=3.6
License-File: LICENSE
Requires-Dist: click
Requires-Dist: androguard >=4.0.0
Requires-Dist: apk-signer
Requires-Dist: pytest
Requires-Dist: colorlog
Requires-Dist: coverage
Requires-Dist: requests
